Workbook
Name do: 'indicators '!#REF!
Name Moji: 'indicators '!$C$46
Name release: 'indicators '!$C$30

Sheet Token Model
A1: Token Details | D1: Token Price | K1: Capitalisation Table
A2: Token Name | B2: TrustPay Coin | D2: Round | E2: Tokens | F2: % Max Supply | G2: Price | H2: Discount | I2: Funding | K2: Round | L2: Pre-Launch | M2: Launch | N2: FDV
A3: Symbol | B3: TXP | D3: seed | E3: 20000000 | F3: 4.00% | G3: 0.03 | H3: 75.00% | I3: 600000 | K3: seed | L3: 600000 | M3: 1635000 | N3: 15000000
A4: Protocol | B4: Ethereum | D4: private | E4: 50000000 | F4: 10.00% | G4: 0.06 | H4: 50.00% | I4: 3000000 | K4: private | L4: 4200000 | M4: 3270000 | N4: 30000000
A5: Starting Price | B5: 0.12 | D5: pre-sale | E5: 50000000 | F5: 10.00% | G5: 0.09 | H5: 25.00% | I5: 4500000 | K5: pre-sale | L5: 10800000 | M5: 4905000 | N5: 45000000
A6: Max Supply | B6: 500000000 | D6: public | E6: 50000000 | F6: 10.00% | G6: 0.12 | H6: 0.00% | I6: 6000000 | K6: public | L6: 20400000 | M6: 6540000 | N6: 60000000
D7: Total pressure
A8: Token Distribution
A9: segments | B9: Tokens | C9: % Max Supply | D9: % on TGE | E9: Release on TGE | F9: LOOK UP MONTHS | G9: LINEAR REALSE
A10: Seed | B10: 20000000 | C10: 0.04 | D10: 0.05 | E10: 1000000 | F10: 6 | G10: 18
A11: Private | B11: 50000000 | C11: 0.1 | D11: 0.05 | E11: 2500000 | F11: 6 | G11: 12
A12: Pre-Sale | B12: 50000000 | C12: 0.1 | D12: 0.05 | E12: 2500000 | F12: 4 | G12: 12
A13: Public | B13: 50000000 | C13: 0.1 | D13: 0.5 | E13: 25000000 | F13: 0 | G13: 3
A14: Team | B14: 40000000 | C14: 0.08 | D14: 0 | E14: 0 | F14: 12 | G14: 12
A15: Advisors | B15: 10000000 | C15: 0.02 | D15: 0 | E15: 0 | F15: 6 | G15: 12
A16: Rewards | B16: 120000000 | C16: 0.24 | D16: 0.05 | E16: 6000000 | F16: 1 | G16: 48 | X16: {=INDEX(A:A, MATCH(TRUE, X:X>=50%, 0))} -> 0
A17: Liquidity | B17: 75000000 | C17: 0.15 | D17: 0.3 | E17: 15000000 | F17: 0 | G17: 12
A18: Treasury | B18: 50000000 | C18: 0.1 | D18: 0.05 | E18: 2500000 | F18: 6 | G18: 18
A19: Reserve | B19: 35000000 | C19: 0.07 | D19: 0 | E19: 0 | F19: 6 | G19: 18
A21: Token Release Schedule
A22: Date | B22: Seed(Cumulative) | C22: Seed(Daily) | D22: Private(Cumulative) | E22: Private(Daily) | F22: Pre-Sale(Cumulative) | G22: Pre-Sale(Daily) | H22: Public(Cumulative) | I22: Public(Daily) | J22: Team(Cumulative) | K22: Team(Daily) | L22: Advisors(Cumulative) | M22: Advisors(Daily) | N22: Rewards(Cumulative) | O22: Rewards(Daily) | P22: Liquidity(Cumulative) | Q22: Liquidity(Daily) | R22: Treasury(Cumulative) | S22: Treasury(Daily) | T22: Reserve(Cumulative) | U22: Reserve(Daily) | V22: Total Cumulative | W22: Total Daily | X22: % Max supply (Cumulative) | Y22: % Max supply (Daily) | Z22: Incremental Drop % | AA22: Remaining supply | AB22: Confidence indicator | AC22: Liquidity Pressure Ratio (LPR)
A23: 45659 | B23: 1000000 | C23: 0 | D23: 2500000 | E23: 0 | F23: 2500000 | G23: 0 | H23: 25277778 | I23: 277777.78 | J23: 0 | K23: 0 | L23: 0 | M23: 0 | N23: 6000000 | O23: 0 | P23: 15166667 | Q23: 166666.67 | R23: 2500000 | S23: 0 | T23: 0 | U23: 0 | V23: 54944444 | W23: 444444.44 | X23: =V23/$B$6 -> 0.10988889 | Y23: =W23/$B$6 -> 0.00088888889 | AA23: =$B$6-V23 -> 4.4505556e+08 | AB23: =W23/AA23 -> 0.00099862689 | AC23: =P23/(V23-P23) -> 0.38128492
A24: 45660 | B24: 1000000 | C24: 0 | D24: 2500000 | E24: 0 | F24: 2500000 | G24: 0 | H24: 25555556 | I24: 277777.78 | J24: 0 | K24: 0 | L24: 0 | M24: 0 | N24: 6000000 | O24: 0 | P24: 15333333 | Q24: 166666.67 | R24: 2500000 | S24: 0 | T24: 0 | U24: 0 | V24: 55388889 | W24: 444444.44 | X24: =V24/$B$6 -> 0.11077778 | Y24: =W24/$B$6 -> 0.00088888889 | Z24: =W24/V23 -> 0.0080889788 | AA24: =$B$6-V24 -> 4.4461111e+08 | AB24: =W24/AA24 -> 0.00099962514 | AC24: =P24/(V24-P24) -> 0.38280166
A25: 45661 | B25: 1000000 | C25: 0 | D25: 2500000 | E25: 0 | F25: 2500000 | G25: 0 | H25: 25833333 | I25: 277777.78 | J25: 0 | K25: 0 | L25: 0 | M25: 0 | N25: 6000000 | O25: 0 | P25: 15500000 | Q25: 166666.67 | R25: 2500000 | S25: 0 | T25: 0 | U25: 0 | V25: 55833333 | W25: 444444.44 | X25: =V25/$B$6 -> 0.11166667 | Y25: =W25/$B$6 -> 0.00088888889 | Z25: =W25/V24 -> 0.0080240722 | AA25: =$B$6-V25 -> 4.4416667e+08 | AB25: =W25/AA25 -> 0.0010006254 | AC25: =P25/(V25-P25) -> 0.38429752
A26: 45662 | B26: 1000000 | C26: 0 | D26: 2500000 | E26: 0 | F26: 2500000 | G26: 0 | H26: 26111111 | I26: 277777.78 | J26: 0 | K26: 0 | L26: 0 | M26: 0 | N26: 6000000 | O26: 0 | P26: 15666667 | Q26: 166666.67 | R26: 2500000 | S26: 0 | T26: 0 | U26: 0 | V26: 56277778 | W26: 444444.44 | X26: =V26/$B$6 -> 0.11255556 | Y26: =W26/$B$6 -> 0.00088888889 | Z26: =W26/V25 -> 0.007960199 | AA26: =$B$6-V26 -> 4.4372222e+08 | AB26: =W26/AA26 -> 0.0010016276 | AC26: =P26/(V26-P26) -> 0.38577291
A27: 45663 | B27: 1000000 | C27: 0 | D27: 2500000 | E27: 0 | F27: 2500000 | G27: 0 | H27: 26388889 | I27: 277777.78 | J27: 0 | K27: 0 | L27: 0 | M27: 0 | N27: 6000000 | O27: 0 | P27: 15833333 | Q27: 166666.67 | R27: 2500000 | S27: 0 | T27: 0 | U27: 0 | V27: 56722222 | W27: 444444.44 | X27: =V27/$B$6 -> 0.11344444 | Y27: =W27/$B$6 -> 0.00088888889 | Z27: =W27/V26 -> 0.0078973346 | AA27: =$B$6-V27 -> 4.4327778e+08 | AB27: =W27/AA27 -> 0.0010026319 | AC27: =P27/(V27-P27) -> 0.38722826
A28: 45664 | B28: 1000000 | C28: 0 | D28: 2500000 | E28: 0 | F28: 2500000 | G28: 0 | H28: 26666667 | I28: 277777.78 | J28: 0 | K28: 0 | L28: 0 | M28: 0 | N28: 6000000 | O28: 0 | P28: 16000000 | Q28: 166666.67 | R28: 2500000 | S28: 0 | T28: 0 | U28: 0 | V28: 57166667 | W28: 444444.44 | X28: =V28/$B$6 -> 0.11433333 | Y28: =W28/$B$6 -> 0.00088888889 | Z28: =W28/V27 -> 0.0078354554 | AA28: =$B$6-V28 -> 4.4283333e+08 | AB28: =W28/AA28 -> 0.0010036382 | AC28: =P28/(V28-P28) -> 0.38866397
A29: 45665 | B29: 1000000 | C29: 0 | D29: 2500000 | E29: 0 | F29: 2500000 | G29: 0 | H29: 26944444 | I29: 277777.78 | J29: 0 | K29: 0 | L29: 0 | M29: 0 | N29: 6000000 | O29: 0 | P29: 16166667 | Q29: 166666.67 | R29: 2500000 | S29: 0 | T29: 0 | U29: 0 | V29: 57611111 | W29: 444444.44 | X29: =V29/$B$6 -> 0.11522222 | Y29: =W29/$B$6 -> 0.00088888889 | Z29: =W29/V28 -> 0.0077745384 | AA29: =$B$6-V29 -> 4.4238889e+08 | AB29: =W29/AA29 -> 0.0010046465 | AC29: =P29/(V29-P29) -> 0.39008043
A30: 45666 | B30: 1000000 | C30: 0 | D30: 2500000 | E30: 0 | F30: 2500000 | G30: 0 | H30: 27222222 | I30: 277777.78 | J30: 0 | K30: 0 | L30: 0 | M30: 0 | N30: 6000000 | O30: 0 | P30: 16333333 | Q30: 166666.67 | R30: 2500000 | S30: 0 | T30: 0 | U30: 0 | V30: 58055556 | W30: 444444.44 | X30: =V30/$B$6 -> 0.11611111 | Y30: =W30/$B$6 -> 0.00088888889 | Z30: =W30/V29 -> 0.0077145612 | AA30: =$B$6-V30 -> 4.4194444e+08 | AB30: =W30/AA30 -> 0.0010056568 | AC30: =P30/(V30-P30) -> 0.39147803
A31: 45667 | B31: 1000000 | C31: 0 | D31: 2500000 | E31: 0 | F31: 2500000 | G31: 0 | H31: 27500000 | I31: 277777.78 | J31: 0 | K31: 0 | L31: 0 | M31: 0 | N31: 6000000 | O31: 0 | P31: 16500000 | Q31: 166666.67 | R31: 2500000 | S31: 0 | T31: 0 | U31: 0 | V31: 58500000 | W31: 444444.44 | X31: =V31/$B$6 -> 0.117 | Y31: =W31/$B$6 -> 0.00088888889 | Z31: =W31/V30 -> 0.0076555024 | AA31: =$B$6-V31 -> 441500000 | AB31: =W31/AA31 -> 0.0010066692 | AC31: =P31/(V31-P31) -> 0.39285714
A32: 45668 | B32: 1000000 | C32: 0 | D32: 2500000 | E32: 0 | F32: 2500000 | G32: 0 | H32: 27777778 | I32: 277777.78 | J32: 0 | K32: 0 | L32: 0 | M32: 0 | N32: 6000000 | O32: 0 | P32: 16666667 | Q32: 166666.67 | R32: 2500000 | S32: 0 | T32: 0 | U32: 0 | V32: 58944444 | W32: 444444.44 | X32: =V32/$B$6 -> 0.11788889 | Y32: =W32/$B$6 -> 0.00088888889 | Z32: =W32/V31 -> 0.0075973409 | AA32: =$B$6-V32 -> 4.4105556e+08 | AB32: =W32/AA32 -> 0.0010076836 | AC32: =P32/(V32-P32) -> 0.39421813
A33: 45669 | B33: 1000000 | C33: 0 | D33: 2500000 | E33: 0 | F33: 2500000 | G33: 0 | H33: 28055556 | I33: 277777.78 | J33: 0 | K33: 0 | L33: 0 | M33: 0 | N33: 6000000 | O33: 0 | P33: 16833333 | Q33: 166666.67 | R33: 2500000 | S33: 0 | T33: 0 | U33: 0 | V33: 59388889 | W33: 444444.44 | X33: =V33/$B$6 -> 0.11877778 | Y33: =W33/$B$6 -> 0.00088888889 | Z33: =W33/V32 -> 0.0075400566 | AA33: =$B$6-V33 -> 4.4061111e+08 | AB33: =W33/AA33 -> 0.0010087 | AC33: =P33/(V33-P33) -> 0.39556136
A34: 45670 | B34: 1000000 | C34: 0 | D34: 2500000 | E34: 0 | F34: 2500000 | G34: 0 | H34: 28333333 | I34: 277777.78 | J34: 0 | K34: 0 | L34: 0 | M34: 0 | N34: 6000000 | O34: 0 | P34: 17000000 | Q34: 166666.67 | R34: 2500000 | S34: 0 | T34: 0 | U34: 0 | V34: 59833333 | W34: 444444.44 | X34: =V34/$B$6 -> 0.11966667 | Y34: =W34/$B$6 -> 0.00088888889 | Z34: =W34/V33 -> 0.0074836296 | AA34: =$B$6-V34 -> 4.4016667e+08 | AB34: =W34/AA34 -> 0.0010097185 | AC34: =P34/(V34-P34) -> 0.39688716
A35: 45671 | B35: 1000000 | C35: 0 | D35: 2500000 | E35: 0 | F35: 2500000 | G35: 0 | H35: 28611111 | I35: 277777.78 | J35: 0 | K35: 0 | L35: 0 | M35: 0 | N35: 6000000 | O35: 0 | P35: 17166667 | Q35: 166666.67 | R35: 2500000 | S35: 0 | T35: 0 | U35: 0 | V35: 60277778 | W35: 444444.44 | X35: =V35/$B$6 -> 0.12055556 | Y35: =W35/$B$6 -> 0.00088888889 | Z35: =W35/V34 -> 0.0074280409 | AA35: =$B$6-V35 -> 4.3972222e+08 | AB35: =W35/AA35 -> 0.0010107391 | AC35: =P35/(V35-P35) -> 0.39819588
... A1492: 47128 | B1492: 20000000 | C1492: 0 | D1492: 50000000 | E1492: 0 | F1492: 50000000 | G1492: 0 | H1492: 50000000 | I1492: 0 | J1492: 40000000 | K1492: 0 | L1492: 10000000 | M1492: 0 | N1492: 120000000 | O1492: 79166.667 | P1492: 75000000 | Q1492: 0 | R1492: 50000000 | S1492: 0 | T1492: 35000000 | U1492: 0 | V1492: 500000000 | W1492: 79166.667 | X1492: =V1492/$B$6 -> 1 | Y1492: =W1492/$B$6 -> 0.00015833333 | Z1492: =W1492/V1491 -> 0.00015835841 | AA1492: =$B$6-V1492 -> 0 | AB1492: =W1492/AA1492 -> #DIV/0! | AC1492: =P1492/(V1492-P1492) -> 0.17647059

Sheet Monthly Release Schedule
A1: Monthly Release Schedule
A2: Date | B2: Seed(Cumulative) | C2: Seed(Monthly) | D2: Private(Cumulative) | E2: Private(Monthly) | F2: Pre-Sale(Cumulative) | G2: Pre-Sale(Monthly) | H2: Public(Cumulative) | I2: Public(Monthly) | J2: Team(Cumulative) | K2: Team(Monthly) | L2: Advisors(Cumulative) | M2: Advisors(Monthly) | N2: Rewards(Cumulative) | O2: Rewards(Monthly) | P2: Liquidity(Cumulative) | Q2: Liquidity(Monthly) | R2: Treasury(Cumulative) | S2: Treasury(Monthly) | T2: Reserve(Cumulative) | U2: Reserve(Monthly) | V2: Total Cumulative | W2: Total Monthly | X2: % Max supply (Cumulative) | Y2: % Max supply (Montly) | Z2: Incremental % Drop | AA2: Remaining supply | AB2: Confidence indicator | AC2: Liquidity Pressure Ratio (LPR)
A3: 45688 | B3: 1000000 | C3: 0 | D3: 2500000 | E3: 0 | F3: 2500000 | G3: 0 | H3: 33333333 | I3: 8333333.3 | J3: 0 | K3: 0 | L3: 0 | M3: 0 | N3: 6000000 | O3: 0 | P3: 20000000 | Q3: 5000000 | R3: 2500000 | S3: 0 | T3: 0 | U3: 0 | V3: 67833333 | W3: 13333333 | X3: =V3/'Token Model'!$B$6 -> 0.13566667 | Y3: =W3/'Token Model'!$B$6 -> 0.026666667 | AA3: ='Token Model'!$B$6-V3 -> 4.3216667e+08 | AB3: =W3/AA3 -> 0.030852295 | AC3: =P3/(V3-P3) -> 0.41811847 | AL3: {=INDEX(A3:A1000000, MATCH(TRUE, X3:X100000>=50%, 0))} -> 46022
A4: 45716 | B4: 1000000 | C4: 0 | D4: 2500000 | E4: 0 | F4: 2500000 | G4: 0 | H4: 41666667 | I4: 8333333.3 | J4: 0 | K4: 0 | L4: 0 | M4: 0 | N4: 8375000 | O4: 2375000 | P4: 25000000 | Q4: 5000000 | R4: 2500000 | S4: 0 | T4: 0 | U4: 0 | V4: 83541667 | W4: 15708333 | X4: =V4/'Token Model'!$B$6 -> 0.16708333 | Y4: =W4/'Token Model'!$B$6 -> 0.031416667 | Z4: =W4/V3 -> 0.23157248 | AA4: ='Token Model'!$B$6-V4 -> 4.1645833e+08 | AB4: =W4/AA4 -> 0.037718859 | AC4: =P4/(V4-P4) -> 0.42704626
A5: 45747 | B5: 1000000 | C5: 0 | D5: 2500000 | E5: 0 | F5: 2500000 | G5: 0 | H5: 50000000 | I5: 8333333.3 | J5: 0 | K5: 0 | L5: 0 | M5: 0 | N5: 10750000 | O5: 2375000 | P5: 30000000 | Q5: 5000000 | R5: 2500000 | S5: 0 | T5: 0 | U5: 0 | V5: 99250000 | W5: 15708333 | X5: =V5/'Token Model'!$B$6 -> 0.1985 | Y5: =W5/'Token Model'!$B$6 -> 0.031416667 | Z5: =W5/V4 -> 0.18802993 | AA5: ='Token Model'!$B$6-V5 -> 400750000 | AB5: =W5/AA5 -> 0.039197338 | AC5: =P5/(V5-P5) -> 0.433213
A6: 45777 | B6: 1000000 | C6: 0 | D6: 2500000 | E6: 0 | F6: 2500000 | G6: 0 | H6: 50000000 | I6: 0 | J6: 0 | K6: 0 | L6: 0 | M6: 0 | N6: 13125000 | O6: 2375000 | P6: 35000000 | Q6: 5000000 | R6: 2500000 | S6: 0 | T6: 0 | U6: 0 | V6: 106625000 | W6: 7375000 | X6: =V6/'Token Model'!$B$6 -> 0.21325 | Y6: =W6/'Token Model'!$B$6 -> 0.01475 | Z6: =W6/V5 -> 0.074307305 | AA6: ='Token Model'!$B$6-V6 -> 393375000 | AB6: =W6/AA6 -> 0.018748014 | AC6: =P6/(V6-P6) -> 0.4886562
A7: 45808 | B7: 1000000 | C7: 0 | D7: 2500000 | E7: 0 | F7: 6458333.3 | G7: 3958333.3 | H7: 50000000 | I7: 0 | J7: 0 | K7: 0 | L7: 0 | M7: 0 | N7: 15500000 | O7: 2375000 | P7: 40000000 | Q7: 5000000 | R7: 2500000 | S7: 0 | T7: 0 | U7: 0 | V7: 1.1795833e+08 | W7: 11333333 | X7: =V7/'Token Model'!$B$6 -> 0.23591667 | Y7: =W7/'Token Model'!$B$6 -> 0.022666667 | Z7: =W7/V6 -> 0.10629152 | AA7: ='Token Model'!$B$6-V7 -> 3.8204167e+08 | AB7: =W7/AA7 -> 0.029665176 | AC7: =P7/(V7-P7) -> 0.5130946
A8: 45838 | B8: 1000000 | C8: 0 | D8: 2500000 | E8: 0 | F8: 10416667 | G8: 3958333.3 | H8: 50000000 | I8: 0 | J8: 0 | K8: 0 | L8: 0 | M8: 0 | N8: 17875000 | O8: 2375000 | P8: 45000000 | Q8: 5000000 | R8: 2500000 | S8: 0 | T8: 0 | U8: 0 | V8: 1.2929167e+08 | W8: 11333333 | X8: =V8/'Token Model'!$B$6 -> 0.25858333 | Y8: =W8/'Token Model'!$B$6 -> 0.022666667 | Z8: =W8/V7 -> 0.096079124 | AA8: ='Token Model'!$B$6-V8 -> 3.7070833e+08 | AB8: =W8/AA8 -> 0.030572103 | AC8: =P8/(V8-P8) -> 0.5338606
A9: 45869 | B9: 2055555.6 | C9: 1055555.6 | D9: 6458333.3 | E9: 3958333.3 | F9: 14375000 | G9: 3958333.3 | H9: 50000000 | I9: 0 | J9: 0 | K9: 0 | L9: 833333.33 | M9: 833333.33 | N9: 20250000 | O9: 2375000 | P9: 50000000 | Q9: 5000000 | R9: 5138888.9 | S9: 2638888.9 | T9: 1944444.4 | U9: 1944444.4 | V9: 1.5105556e+08 | W9: 21763889 | X9: =V9/'Token Model'!$B$6 -> 0.30211111 | Y9: =W9/'Token Model'!$B$6 -> 0.043527778 | Z9: =W9/V8 -> 0.16833172 | AA9: ='Token Model'!$B$6-V9 -> 3.4894444e+08 | AB9: =W9/AA9 -> 0.062370642 | AC9: =P9/(V9-P9) -> 0.49477735
A10: 45900 | B10: 3111111.1 | C10: 1055555.6 | D10: 10416667 | E10: 3958333.3 | F10: 18333333 | G10: 3958333.3 | H10: 50000000 | I10: 0 | J10: 0 | K10: 0 | L10: 1666666.7 | M10: 833333.33 | N10: 22625000 | O10: 2375000 | P10: 55000000 | Q10: 5000000 | R10: 7777777.8 | S10: 2638888.9 | T10: 3888888.9 | U10: 1944444.4 | V10: 1.7281944e+08 | W10: 21763889 | X10: =V10/'Token Model'!$B$6 -> 0.34563889 | Y10: =W10/'Token Model'!$B$6 -> 0.043527778 | Z10: =W10/V9 -> 0.14407871 | AA10: ='Token Model'!$B$6-V10 -> 3.2718056e+08 | AB10: =W10/AA10 -> 0.066519506 | AC10: =P10/(V10-P10) -> 0.46681598
A11: 45930 | B11: 4166666.7 | C11: 1055555.6 | D11: 14375000 | E11: 3958333.3 | F11: 22291667 | G11: 3958333.3 | H11: 50000000 | I11: 0 | J11: 0 | K11: 0 | L11: 2500000 | M11: 833333.33 | N11: 25000000 | O11: 2375000 | P11: 60000000 | Q11: 5000000 | R11: 10416667 | S11: 2638888.9 | T11: 5833333.3 | U11: 1944444.4 | V11: 1.9458333e+08 | W11: 21763889 | X11: =V11/'Token Model'!$B$6 -> 0.38916667 | Y11: =W11/'Token Model'!$B$6 -> 0.043527778 | Z11: =W11/V10 -> 0.12593426 | AA11: ='Token Model'!$B$6-V11 -> 3.0541667e+08 | AB11: =W11/AA11 -> 0.071259663 | AC11: =P11/(V11-P11) -> 0.44582043
A12: 45961 | B12: 5222222.2 | C12: 1055555.6 | D12: 18333333 | E12: 3958333.3 | F12: 26250000 | G12: 3958333.3 | H12: 50000000 | I12: 0 | J12: 0 | K12: 0 | L12: 3333333.3 | M12: 833333.33 | N12: 27375000 | O12: 2375000 | P12: 65000000 | Q12: 5000000 | R12: 13055556 | S12: 2638888.9 | T12: 7777777.8 | U12: 1944444.4 | V12: 2.1634722e+08 | W12: 21763889 | X12: =V12/'Token Model'!$B$6 -> 0.43269444 | Y12: =W12/'Token Model'!$B$6 -> 0.043527778 | Z12: =W12/V11 -> 0.11184868 | AA12: ='Token Model'!$B$6-V12 -> 2.8365278e+08 | AB12: =W12/AA12 -> 0.076727219 | AC12: =P12/(V12-P12) -> 0.429476
A13: 45991 | B13: 6277777.8 | C13: 1055555.6 | D13: 22291667 | E13: 3958333.3 | F13: 30208333 | G13: 3958333.3 | H13: 50000000 | I13: 0 | J13: 0 | K13: 0 | L13: 4166666.7 | M13: 833333.33 | N13: 29750000 | O13: 2375000 | P13: 70000000 | Q13: 5000000 | R13: 15694444 | S13: 2638888.9 | T13: 9722222.2 | U13: 1944444.4 | V13: 2.3811111e+08 | W13: 21763889 | X13: =V13/'Token Model'!$B$6 -> 0.47622222 | Y13: =W13/'Token Model'!$B$6 -> 0.043527778 | Z13: =W13/V12 -> 0.10059703 | AA13: ='Token Model'!$B$6-V13 -> 2.6188889e+08 | AB13: =W13/AA13 -> 0.083103521 | AC13: =P13/(V13-P13) -> 0.41639128
A14: 46022 | B14: 7333333.3 | C14: 1055555.6 | D14: 26250000 | E14: 3958333.3 | F14: 34166667 | G14: 3958333.3 | H14: 50000000 | I14: 0 | J14: 0 | K14: 0 | L14: 5000000 | M14: 833333.33 | N14: 32125000 | O14: 2375000 | P14: 75000000 | Q14: 5000000 | R14: 18333333 | S14: 2638888.9 | T14: 11666667 | U14: 1944444.4 | V14: 259875000 | W14: 21763889 | X14: =V14/'Token Model'!$B$6 -> 0.51975 | Y14: =W14/'Token Model'!$B$6 -> 0.043527778 | Z14: =W14/V13 -> 0.09140224 | AA14: ='Token Model'!$B$6-V14 -> 240125000 | AB14: =W14/AA14 -> 0.090635664 | AC14: =P14/(V14-P14) -> 0.40567951
A15: 46053 | B15: 8388888.9 | C15: 1055555.6 | D15: 30208333 | E15: 3958333.3 | F15: 38125000 | G15: 3958333.3 | H15: 50000000 | I15: 0 | J15: 3333333.3 | K15: 3333333.3 | L15: 5833333.3 | M15: 833333.33 | N15: 34500000 | O15: 2375000 | P15: 75000000 | Q15: 0 | R15: 20972222 | S15: 2638888.9 | T15: 13611111 | U15: 1944444.4 | V15: 2.7997222e+08 | W15: 20097222 | X15: =V15/'Token Model'!$B$6 -> 0.55994444 | Y15: =W15/'Token Model'!$B$6 -> 0.040194444 | Z15: =W15/V14 -> 0.077334188 | AA15: ='Token Model'!$B$6-V15 -> 2.2002778e+08 | AB15: =W15/AA15 -> 0.091339477 | AC15: =P15/(V15-P15) -> 0.36590324
... A50: 47118 | B50: 20000000 | C50: 0 | D50: 50000000 | E50: 0 | F50: 50000000 | G50: 0 | H50: 50000000 | I50: 0 | J50: 40000000 | K50: 0 | L50: 10000000 | M50: 0 | N50: 117625000 | O50: 2375000 | P50: 75000000 | Q50: 0 | R50: 50000000 | S50: 0 | T50: 35000000 | U50: 0 | V50: 497625000 | W50: 2375000 | X50: =V50/'Token Model'!$B$6 -> 0.99525 | Y50: =W50/'Token Model'!$B$6 -> 0.00475 | Z50: =W50/V49 -> 0.0047955578 | AA50: ='Token Model'!$B$6-V50 -> 2375000 | AB50: =W50/AA50 -> 1 | AC50: =P50/(V50-P50) -> 0.17746229
A51: 47149 | B51: 20000000 | C51: 0 | D51: 50000000 | E51: 0 | F51: 50000000 | G51: 0 | H51: 50000000 | I51: 0 | J51: 40000000 | K51: 0 | L51: 10000000 | M51: 0 | N51: 120000000 | O51: 2375000 | P51: 75000000 | Q51: 0 | R51: 50000000 | S51: 0 | T51: 35000000 | U51: 0 | V51: 500000000 | W51: 2375000 | X51: =V51/'Token Model'!$B$6 -> 1 | Y51: =W51/'Token Model'!$B$6 -> 0.00475 | Z51: =W51/V50 -> 0.0047726702 | AA51: ='Token Model'!$B$6-V51 -> 0 | AC51: =P51/(V51-P51) -> 0.17647059
V59: =AVERAGE(W3:W51) -> 9091836.7

Sheet indicators 
C1: Key metrics | I1: Supply metrics
C2: Initial Circulating Supply: | D2: =SUM('Token Model'!$E$10:$E$19) -> 54500000 | H2: Q1 | I2: Q2 | J2: Q3 | K2: Q4 | L2: Y1 | M2: Y2 | N2: Y3 | O2: Y4 | P2: Y5
C3: Target Raise : | D3: =SUM(('Token Model'!E3*'Token Model'!G3),('Token Model'!E4*'Token Model'!G4),('Token Model'!E5*'Token Model'!G5),('Token Model'!E6*'Token Model'!G6)) -> 14100000 | G3: Avg. Release (D) | H3: =AVERAGE('Token Model'!$W$23:$W$112) -> 497222.22 | I3: =AVERAGE('Token Model'!$W$113:$W$203) -> 338100.33 | J3: =AVERAGE('Token Model'!$W$204:$W$295) -> 725462.96 | K3: =AVERAGE('Token Model'!$W$296:$W$387) -> 722443.64 | L3: =AVERAGE('Token Model'!$W$23:$W$387) -> 571848.05 | M3: =AVERAGE('Token Model'!$W$388:'Token Model'!$W$752) -> 488197.62 | N3: =AVERAGE('Token Model'!$W$753:'Token Model'!$W$1117) -> 79166.667 | O3: =AVERAGE('Token Model'!$W$1118:'Token Model'!$W$1483) -> 79166.667 | P3: =AVERAGE('Token Model'!$W$1484:$W$1492) -> 79166.667
C4: Initial Marketcap: | D4: =(SUM('Token Model'!$E$10:$E$19)-'Token Model'!$E$17)*'Token Model'!$B$5 -> 4740000 | G4: Avg. Release (M) | H4: =AVERAGE('Monthly Release Schedule'!$W$3:$W$5) -> 14916667 | I4: =AVERAGE('Monthly Release Schedule'!$W$6:$W$8) -> 10013889 | J4: =AVERAGE('Monthly Release Schedule'!$W$9:$W$11) -> 21763889 | K4: =AVERAGE('Monthly Release Schedule'!$W$12:$W$14) -> 21763889 | L4: =AVERAGE('Monthly Release Schedule'!$W$3:$W$14) -> 17114583 | M4: =AVERAGE('Monthly Release Schedule'!$W$15:$W$26) -> 15062500 | N4: =AVERAGE('Monthly Release Schedule'!$W$27:$W$38) -> 2375000 | O4: =AVERAGE('Monthly Release Schedule'!$W$39:$W$50) -> 2375000 | P4: =AVERAGE('Monthly Release Schedule'!$W$51:$W$51) -> 2375000
C5: Initial Marketcap, including liquidiy : | D5: =SUM('Token Model'!$E$10:$E$19)*'Token Model'!$B$5 -> 6540000 | G5: Total Release | H5: =SUM('Monthly Release Schedule'!$W$3:$W$5) -> 44750000 | I5: =SUM('Monthly Release Schedule'!$W$6:$W$8) -> 30041667 | J5: =SUM('Monthly Release Schedule'!$W$9:$W$11) -> 65291667 | K5: =SUM('Monthly Release Schedule'!$W$12:$W$14) -> 65291667 | L5: =SUM('Monthly Release Schedule'!$W$3:$W$14) -> 2.05375e+08 | M5: =SUM('Monthly Release Schedule'!$W$15:$W$26) -> 1.8075e+08 | N5: =SUM('Monthly Release Schedule'!$W$27:$W$38) -> 28500000 | O5: =SUM('Monthly Release Schedule'!$W$39:$W$50) -> 28500000 | P5: =SUM('Monthly Release Schedule'!$W$51:$W$51) -> 2375000
C6: Fully Dilluted Marketcap: | D6: ='Token Model'!$B$6*'Token Model'!$B$5 -> 60000000 | G6: % Max supply(Avg. Release (M)) | H6: =$H$4/'Token Model'!$B$6 -> 0.029833333 | I6: =$I$4/'Token Model'!$B$6 -> 0.020027778 | J6: =$J$4/'Token Model'!$B$6 -> 0.043527778 | K6: =$K$4/'Token Model'!$B$6 -> 0.043527778 | L6: =$L$4/'Token Model'!$B$6 -> 0.034229167 | M6: =$M$4/'Token Model'!$B$6 -> 0.030125 | N6: =$N$4/'Token Model'!$B$6 -> 0.00475 | O6: =$O$4/'Token Model'!$B$6 -> 0.00475 | P6: =$P$4/'Token Model'!$B$6 -> 0.00475
C7: Liquidity pressure Ratio on TGE | D7: ='Token Model'!$E$17/(SUM('Token Model'!$E$10:$E$19)-'Token Model'!$E$17) -> 0.37974684 | G7: % Max supply(Total Release) | H7: =$H$5/'Token Model'!$B$6 -> 0.0895 | I7: =$I$5/'Token Model'!$B$6 -> 0.060083333 | J7: =$J$5/'Token Model'!$B$6 -> 0.13058333 | K7: =$K$5/'Token Model'!$B$6 -> 0.13058333 | L7: =$L$5/'Token Model'!$B$6 -> 0.41075 | M7: =$M$5/'Token Model'!$B$6 -> 0.3615 | N7: =$N$5/'Token Model'!$B$6 -> 0.057 | O7: =$O$5/'Token Model'!$B$6 -> 0.057 | P7: =$P$5/'Token Model'!$B$6 -> 0.00475
C8: Lock-Up Ratio on TGE | D8: =('Token Model'!$B$6-SUM('Token Model'!$E$10:$E$19))/'Token Model'!$B$6 -> 0.891
C9: Half-Life of Token Supply | D9: 46022
C16: Sale Pressure Metrics
C17: ROI | D17: seed: | E17: ='Token Model'!$B$5/'Token Model'!G3-1 -> 3
D18: private: | E18: ='Token Model'!$B$5/'Token Model'!G4-1 -> 1
D19: pre-sale: | E19: ='Token Model'!$B$5/'Token Model'!G5-1 -> 0.33333333
C20: Realized Profit on TGE ($) | D20: seed: | E20: ='Token Model'!E10*('Token Model'!$B$5-'Token Model'!$G$3) -> 90000 | F20: =E20/('Token Model'!G3*'Token Model'!E3) -> 0.15
D21: private: | E21: ='Token Model'!$E$11*('Token Model'!$B$5-'Token Model'!$G$4) -> 150000
D22: pre-sale: | E22: ='Token Model'!$E$12*('Token Model'!$B$5-'Token Model'!$G$5) -> 75000
C23: Sale Pressure Indicator on TGE | D23: seed: | E23: =$E$20/$D$4 -> 0.018987342
D24: private: | E24: =$E$21/$D$4 -> 0.03164557
D25: pre-sale: | E25: =$E$22/$D$4 -> 0.015822785
C26: Long-term Realized Profit ($) | D26: seed: | E26: ='Token Model'!$E$3*('Token Model'!$B$5-'Token Model'!$G$3) -> 1800000
D27: private: | E27: ='Token Model'!$E$4*('Token Model'!$B$5-'Token Model'!$G$4) -> 3000000
D28: pre-sale: | E28: ='Token Model'!$E$5*('Token Model'!$B$5-'Token Model'!$G$5) -> 1500000 | I28: Sreess metrics
C29: Total Sale Pressure | D29: seed: | E29: =E26/D6 -> 0.03 | I29: Q1 | J29: Q2 | K29: Q3 | L29: Q4 | M29: Y1 | N29: Y2 | O29: Y3 | P29: Y4 | Q29: Y5
D30: private: | E30: =E27/D6 -> 0.05 | G30: Avg. D | H30: Infaltion (Incremental drop) | I30: =AVERAGE('Token Model'!$Z$23:$Z$112) -> 0.0066664501 | J30: =AVERAGE('Token Model'!$Z$113:$Z$203) -> 0.0029718309 | K30: =AVERAGE('Token Model'!$Z$204:$Z$295) -> 0.0045137489 | L30: =AVERAGE('Token Model'!$Z$296:$Z$387) -> 0.003168356 | M30: =AVERAGE('Token Model'!$Z$23:$Z$387) -> 0.0043145723 | N30: =AVERAGE('Token Model'!$Z$388:'Token Model'!$Z$752) -> 0.0014175817 | O30: =AVERAGE('Token Model'!$Z$753:'Token Model'!$Z$1117) -> 0.00017373596 | P30: =AVERAGE('Token Model'!$Z$1118:'Token Model'!$Z$1483) -> 0.00016335956 | Q30: =AVERAGE('Token Model'!$Z$1484:$Z$1492) -> 0.00015845881
D31: pre-sale: | E31: =E28/D6 -> 0.025 | H31: Confidence indicator | I31: =AVERAGE('Token Model'!$AB$23:$AB$112) -> 0.0011769151 | J31: =AVERAGE('Token Model'!$AB$113:$AB$203) -> 0.00087822115 | K31: =AVERAGE('Token Model'!$AB$204:$AB$295) -> 0.0021646431 | L31: =AVERAGE('Token Model'!$AB$296:$AB$387) -> 0.0026929093 | M31: =AVERAGE('Token Model'!$AB$23:$AB$387) -> 0.0017335214 | N31: =AVERAGE('Token Model'!$AB$388:'Token Model'!$AB$752) -> 0.0038342059 | O31: =AVERAGE('Token Model'!$AB$753:'Token Model'!$AB$1117) -> 0.001864061 | P31: =AVERAGE('Token Model'!$AB$1118:'Token Model'!$AB$1483) -> 0.010341395 | Q31: =AVERAGE('Token Model'!$AB$1484:$AB$1491) -> 0.33973214
H32: Liquidity Pressure Ratio (LPR) | I32: =AVERAGE('Token Model'!$AC$23:$AC$112) -> 0.41807641 | J32: =AVERAGE('Token Model'!$AC$113:$AC$203) -> 0.49636304 | K32: =AVERAGE('Token Model'!$AC$204:$AC$295) -> 0.48075849 | L32: =AVERAGE('Token Model'!$AC$296:$AC$387) -> 0.42151889 | M32: =AVERAGE('Token Model'!$AC$23:$AC$387) -> 0.45426146 | N32: =AVERAGE('Token Model'!$AC$388:'Token Model'!$AC$752) -> 0.26638271 | O32: =AVERAGE('Token Model'!$AC$753:'Token Model'!$AC$1117) -> 0.19699443 | P32: =AVERAGE('Token Model'!$AC$1118:'Token Model'!$AC$1483) -> 0.18307471 | Q32: =AVERAGE('Token Model'!$AC$1484:$AC$1492) -> 0.17660222
G33: Avg. M | H33: Infaltion (Incremental drop) | I33: =AVERAGE('Monthly Release Schedule'!$Z$3:$Z$5) -> 0.2098012 | J33: =AVERAGE('Monthly Release Schedule'!$Z$6:$Z$8) -> 0.092225983 | K33: =AVERAGE('Monthly Release Schedule'!$Z$9:$Z$11) -> 0.1461149 | L33: =AVERAGE('Monthly Release Schedule'!$Z$12:$Z$14) -> 0.10128265 | M33: =AVERAGE('Monthly Release Schedule'!$Z$3:$Z$14) -> 0.13077027 | N33: =AVERAGE('Monthly Release Schedule'!$Z$15:$Z$26) -> 0.045149768 | O33: =AVERAGE('Monthly Release Schedule'!$Z$27:$Z$38) -> 0.0052365914 | P33: =AVERAGE('Monthly Release Schedule'!$Z$39:$Z$50) -> 0.0049268946 | Q33: =AVERAGE('Monthly Release Schedule'!$Z$51:$Z$51) -> 0.0047726702
H34: Confidence indicator | I34: =AVERAGE('Monthly Release Schedule'!$AB$3:$AB$5) -> 0.035922831 | J34: =AVERAGE('Monthly Release Schedule'!$AB$6:$AB$8) -> 0.026328431 | K34: =AVERAGE('Monthly Release Schedule'!$AB$9:$AB$11) -> 0.066716604 | L34: =AVERAGE('Monthly Release Schedule'!$AB$12:$AB$14) -> 0.083488802 | M34: =AVERAGE('Monthly Release Schedule'!$AB$3:$AB$14) -> 0.053114167 | N34: =AVERAGE('Monthly Release Schedule'!$AB$15:$AB$26) -> 0.12381436 | O34: =AVERAGE('Monthly Release Schedule'!$AB$27:$AB$38) -> 0.056062292 | P34: =AVERAGE('Monthly Release Schedule'!$AB$39:$AB$50) -> 0.25860089 | Q34: =AVERAGE('Monthly Release Schedule'!$AB$50:$AB$51) -> 1
H35: Liquidity Pressure Ratio (LPR) | I35: =AVERAGE('Monthly Release Schedule'!$AB$3:$AC$5) -> 0.23102437 | J35: =AVERAGE('Monthly Release Schedule'!$AC$6:$AC$8) -> 0.51187047 | K35: =AVERAGE('Monthly Release Schedule'!$AC$9:$AC$11) -> 0.46913792 | L35: =AVERAGE('Monthly Release Schedule'!$AC$12:$AC$14) -> 0.41718226 | M35: =AVERAGE('Monthly Release Schedule'!$AC$3:$AC$14) -> 0.45607914 | N35: =AVERAGE('Monthly Release Schedule'!$AC$15:$AC$26) -> 0.26209149 | O35: =AVERAGE('Monthly Release Schedule'!$AC$27:$AC$38) -> 0.19690929 | P35: =AVERAGE('Monthly Release Schedule'!$AC$39:$AC$50) -> 0.18319567 | Q35: =AVERAGE('Monthly Release Schedule'!$AC$50:$AC$51) -> 0.17696644
H36: Threthold liquidify | I36: 0.1 | J36: 0.1 | K36: 0.1 | L36: 0.1 | M36: 0.1 | N36: 0.1 | O36: 0.1 | P36: 0.1 | Q36: 0.1
